scHyper/__init__.py
scHyper/dataprocess.py
scHyper/model/Modules.py
scHyper/model/__init__.py
scHyper/model/datapipe.py
scHyper/model/main_torch.py
scHyper/model/torchsummary.py
scHyper/model/utils.py
scHyper-1.0.13.dist-info/METADATA
scHyper-1.0.13.dist-info/WHEEL
scHyper-1.0.13.dist-info/top_level.txt
scHyper-1.0.13.dist-info/RECORD
