Metadata-Version: 2.1
Name: scHyper
Version: 1.0.13
Summary: scHyper: Reconstructing cell-cell communication through hypergraph neural networks
Home-page: https://github.com/Lwyonly/scHyper
Author: Li
Author-email: contact@author.com
License: MIT
Platform: UNKNOWN
Requires-Dist: numpy (>=1.24.3)
Requires-Dist: scipy (==1.11.2)
Requires-Dist: pandas (==2.1.4)
Requires-Dist: torch (>=2.0.1)
Requires-Dist: scikit-learn (>=1.3.0)
Requires-Dist: tqdm
Requires-Dist: h5py
